Workbook

Sheet Messages
A1: Message ID | B1: Message Text (synthetic) | C1: Category | D1: Ground Truth | E1: Signals / Rationale | F1: Language | G1: Source Type | H1: Privacy Checked | I1: Review Status | J1: Notes
A2: MSG001 | B2: Your bank account will be blocked today. Share your OTP immediately to verify. | C2: Banking | D2: Scam | E2: OTP request; urgency | F2: English | G2: Synthetic | H2: Yes | I2: Reviewed | J2: Illustrative only; not a verified incident
A3: MSG002 | B3: KYC update pending. Send your one-time password to avoid account suspension. | C3: Banking | D3: Scam | E3: Credential request; impersonation | F3: English | G3: Synthetic | H3: Yes | I3: Reviewed | J3: Illustrative only; not a verified incident
A4: MSG003 | B4: Dear customer, confirm your ATM PIN with our agent to restore banking access. | C4: Banking | D4: Scam | E4: PIN request; impersonation | F4: English | G4: Synthetic | H4: Yes | I4: Reviewed | J4: Illustrative only; not a verified incident
A5: MSG004 | B5: Your savings account is frozen. Reply with your password to unlock it. | C5: Banking | D5: Scam | E5: Password request; urgency | F5: English | G5: Synthetic | H5: Yes | I5: Reviewed | J5: Illustrative only; not a verified incident
A6: MSG005 | B6: Bank verification failed. Transfer Rs 250 as an activation charge today. | C6: Banking | D6: Scam | E6: Advance fee; impersonation | F6: English | G6: Synthetic | H6: Yes | I6: Reviewed | J6: Illustrative only; not a verified incident
A7: MSG006 | B7: To receive your refund, enter your UPI PIN in the payment request. | C7: UPI | D7: Scam | E7: UPI PIN; refund pretext | F7: English | G7: Synthetic | H7: Yes | I7: Reviewed | J7: Illustrative only; not a verified incident
A8: MSG007 | B8: You won a cashback reward. Approve the collect request to claim Rs 5000. | C8: UPI | D8: Scam | E8: Collect request; prize pretext | F8: English | G8: Synthetic | H8: Yes | I8: Reviewed | J8: Illustrative only; not a verified incident
A9: MSG008 | B9: Please send Rs 100 to verify your UPI account and get the full refund. | C9: UPI | D9: Scam | E9: Advance payment; refund pretext | F9: English | G9: Synthetic | H9: Yes | I9: Reviewed | J9: Illustrative only; not a verified incident
A10: MSG009 | B10: A customer sent you money by mistake. Scan this payment QR to receive the reversal. | C10: UPI | D10: Scam | E10: QR manipulation; payment confusion | F10: English | G10: Synthetic | H10: Yes | I10: Reviewed | J10: Illustrative only; not a verified incident
A11: MSG010 | B11: Aapka refund ready hai. UPI PIN share karo abhi. | C11: UPI | D11: Scam | E11: UPI PIN; urgency | F11: Hinglish | G11: Synthetic | H11: Yes | I11: Reviewed | J11: Illustrative only; not a verified incident
A12: MSG011 | B12: Congratulations, you are selected for a remote job. Pay Rs 999 registration fee today. | C12: Jobs | D12: Scam | E12: Job advance fee | F12: English | G12: Synthetic | H12: Yes | I12: Reviewed | J12: Illustrative only; not a verified incident
... A31: MSG030 | B31: Please contact our support team to update your account information. | C31: Banking | D31: Uncertain | E31: Insufficient context | F31: English | G31: Synthetic | H31: Yes | I31: Reviewed | J31: Illustrative only; not a verified incident

Sheet Keywords
A1: Pattern Name | B1: Category | C1: Example Phrase | D1: Default Concern | E1: Why It Matters | F1: False-positive Caveat
A2: OTP share request | B2: Banking | C2: share your OTP | D2: High | E2: Request for authentication code | F2: Not every OTP mention is malicious
A3: PIN disclosure | B3: Banking | C3: share your PIN | D3: High | E3: Requests sensitive PIN | F3: Distinguish warnings from requests
A4: UPI PIN | B4: UPI | C4: UPI PIN | D4: High | E4: PIN used to authorize payments | F4: Context matters
A5: Registration fee | B5: Jobs | C5: registration fee | D5: Review | E5: Upfront fee associated with job | F5: Some legitimate fees exist
A6: Joining fee | B6: Jobs | C6: joining fee | D6: Review | E6: Job onboarding payment request | F6: Verify independently
A7: Training fee | B7: Jobs | C7: training fee | D7: Review | E7: Potential employment advance fee | F7: Context matters
A8: Guaranteed profit | B8: Investment | C8: guaranteed profit | D8: Review | E8: Unrealistic investment assurance | F8: Verify regulated disclosures
A9: Risk-free returns | B9: Investment | C9: risk-free | D9: Review | E9: Claims absence of investment risk | F9: Context matters
A10: Account blocked | B10: Banking | C10: account blocked | D10: Review | E10: Urgency and account threat | F10: Could be a warning
A11: Immediately | B11: General | C11: immediately | D11: Review | E11: Urgency cue | F11: Often appears legitimately
A12: OTP disclosure | B12: Banking | C12: send your one-time password | D12: High | E12: Requests a confidential authentication code that could enable account takeover | F12: A security advisory might quote this phrase
... A24: Redelivery fee | B24: Shopping | C24: redelivery fee | D24: Review | E24: May impersonate a courier to obtain payment | F24: Genuine couriers sometimes charge fees

Sheet Sheet1
A1: OTP disclosure | B1: Requests a confidential authentication code that could enable account takeover | C1: A security advisory might quote this phrase
A2: ATM PIN request | B2: Requests disclosure of a sensitive banking PIN | C2: Educational warnings may mention PIN requests
A3: Password request | B3: Requests credentials through an insecure messaging channel | C3: Safety notices may quote phishing wording
A4: Account activation charge | B4: Requests payment to activate or restore banking access | C4: Some genuine products have service charges
A5: UPI verification payment | B5: May pressure users into unnecessary verification payments | C5: Legitimate providers may request non-payment verification
A6: Collect request | B6: May trick recipients into authorizing a debit | C6: Known contacts may send genuine collect requests
A7: Payment QR | B7: May initiate a payment rather than receive funds | C7: Merchants commonly use QR codes
A8: Task activation | B8: May indicate a task-based advance-fee job scam | C8: Legitimate platforms also activate tasks
A9: Recruiter transfer | B9: May indicate an advance-fee recruitment scam | C9: The amount may appear in unrelated transactions
A10: Guaranteed profit | B10: Promises implausibly high guaranteed returns | C10: Educational materials may quote such claims
A11: Double money | B11: Promises unusually high returns | C11: May appear in hypothetical examples
A12: Investment urgency | B12: Creates scarcity pressure | C12: Genuine events can have limited availability
A13: Redelivery fee | B13: May impersonate a courier to obtain payment | C13: Genuine couriers sometimes charge fees

Sheet Test Results
A1: Message ID | B1: Expected Label | C1: Rule Prediction | D1: Gemma Prediction | E1: Rule Correct? | F1: Gemma Correct? | G1: AI Explanation Notes | H1: Test Status
A2: MSG001 | B2: Scam | E2: =IF(C2="","",IF(B2=C2,1,0)) | F2: =IF(D2="","",IF(B2=D2,1,0)) | H2: Not Run
A3: MSG002 | B3: Scam | E3: =IF(C3="","",IF(B3=C3,1,0)) | F3: =IF(D3="","",IF(B3=D3,1,0)) | H3: Not Run
A4: MSG003 | B4: Scam | E4: =IF(C4="","",IF(B4=C4,1,0)) | F4: =IF(D4="","",IF(B4=D4,1,0)) | H4: Not Run
A5: MSG004 | B5: Scam | E5: =IF(C5="","",IF(B5=C5,1,0)) | F5: =IF(D5="","",IF(B5=D5,1,0)) | H5: Not Run
A6: MSG005 | B6: Scam | E6: =IF(C6="","",IF(B6=C6,1,0)) | F6: =IF(D6="","",IF(B6=D6,1,0)) | H6: Not Run
A7: MSG006 | B7: Scam | E7: =IF(C7="","",IF(B7=C7,1,0)) | F7: =IF(D7="","",IF(B7=D7,1,0)) | H7: Not Run
A8: MSG007 | B8: Scam | E8: =IF(C8="","",IF(B8=C8,1,0)) | F8: =IF(D8="","",IF(B8=D8,1,0)) | H8: Not Run
A9: MSG008 | B9: Scam | E9: =IF(C9="","",IF(B9=C9,1,0)) | F9: =IF(D9="","",IF(B9=D9,1,0)) | H9: Not Run
A10: MSG009 | B10: Scam | E10: =IF(C10="","",IF(B10=C10,1,0)) | F10: =IF(D10="","",IF(B10=D10,1,0)) | H10: Not Run
A11: MSG010 | B11: Scam | E11: =IF(C11="","",IF(B11=C11,1,0)) | F11: =IF(D11="","",IF(B11=D11,1,0)) | H11: Not Run
A12: MSG011 | B12: Scam | E12: =IF(C12="","",IF(B12=C12,1,0)) | F12: =IF(D12="","",IF(B12=D12,1,0)) | H12: Not Run
A13: MSG012 | B13: Scam | E13: =IF(C13="","",IF(B13=C13,1,0)) | F13: =IF(D13="","",IF(B13=D13,1,0)) | H13: Not Run
... A31: MSG030 | B31: Uncertain | E31: =IF(C31="","",IF(B31=C31,1,0)) | F31: =IF(D31="","",IF(B31=D31,1,0)) | H31: Not Run

Sheet Dashboard
A1: SCAMSHIELD AI — DATASET OVERVIEW | B1: Value | D1: Category | E1: Count
A2: Total messages | B2: =COUNTA(Messages!A2:A1000) -> 30 | D2: Banking | E2: =COUNTIF(Messages!C2:C1000,D2) -> 8
A3: Scam examples | B3: =COUNTIF(Messages!D2:D1000,"Scam") -> 20 | D3: UPI | E3: =COUNTIF(Messages!C2:C1000,D3) -> 7
A4: Legitimate examples | B4: =COUNTIF(Messages!D2:D1000,"Legitimate") -> 9 | D4: Jobs | E4: =COUNTIF(Messages!C2:C1000,D4) -> 7
A5: Uncertain examples | B5: =COUNTIF(Messages!D2:D1000,"Uncertain") -> 1 | D5: Investment | E5: =COUNTIF(Messages!C2:C1000,D5) -> 5
A6: Rule tests completed | B6: =COUNT('Test Results'!E2:E1000) -> 0 | D6: Delivery | E6: =COUNTIF(Messages!C2:C1000,D6) -> 1
A7: Rule accuracy (tested) | B7: =IFERROR(SUM('Test Results'!E2:E1000)/B6,0) -> 0 | D7: Shopping | E7: =COUNTIF(Messages!C2:C1000,D7) -> 1
A8: Gemma tests completed | B8: =COUNT('Test Results'!F2:F1000) -> 0 | D8: Personal | E8: =COUNTIF(Messages!C2:C1000,D8) -> 1
A9: Gemma accuracy (tested) | B9: =IFERROR(SUM('Test Results'!F2:F1000)/B8,0) -> 0

Sheet Read Me
A1: ScamShield AI — Dataset Guide | B1: Instructions
A2: Purpose | B2: Synthetic examples for developing and testing a fraud-awareness MVP.
A3: Messages | B3: Add messages and label Scam, Legitimate, or Uncertain; record provenance.
A4: Keywords | B4: Treat phrases as signals, not definitive fraud labels.
A5: Test Results | B5: Enter exact predicted labels; accuracy updates automatically.
A6: Privacy | B6: Do not add real OTPs, PINs, account details, phone numbers, or victim identifiers.
A7: AI usage | B7: Excel does not train Gemma automatically. Use labeled examples for evaluation.
A8: Data quality | B8: Keep synthetic and verified real-world sources clearly separated.
A9: Sharing | B9: Review and sanitize all data before publishing this workbook on GitHub.
